pinetext/__init__.py
pinetext/cli.py
pinetext/client.py
pinetext/settings.py
pinetext-0.1.8.dist-info/METADATA
pinetext-0.1.8.dist-info/WHEEL
pinetext-0.1.8.dist-info/entry_points.txt
pinetext-0.1.8.dist-info/licenses/LICENSE
pinetext-0.1.8.dist-info/RECORD
