Metadata-Version: 2.4
Name: pinetext
Version: 0.1.8
Summary: PineText
License-File: LICENSE
Requires-Python: >=3.13
Requires-Dist: pinecone-plugin-assistant>=3.0.0
Requires-Dist: pinecone>=8.0.0
Requires-Dist: pydantic-settings>=2.12.0
Requires-Dist: typer>=0.21.0
Requires-Dist: wandb>=0.23.1
Requires-Dist: weave>=0.52.23
